pytest_check_mk-0.1.1.dist-info/RECORD
pytest_check_mk-0.1.1.dist-info/WHEEL
pytest_check_mk-0.1.1.dist-info/metadata.json
pytest_check_mk-0.1.1.dist-info/DESCRIPTION.rst
pytest_check_mk-0.1.1.dist-info/METADATA
pytest_check_mk-0.1.1.dist-info/entry_points.txt
pytest_check_mk-0.1.1.dist-info/top_level.txt
pytest_check_mk/wrapper.py
pytest_check_mk/plugin.py
pytest_check_mk/file_loader.py
pytest_check_mk/assertions.py
pytest_check_mk/__init__.py
pytest_check_mk/_version.py
