Metadata-Version: 2.0
Name: pytest-check-mk
Version: 0.1.1
Summary: pytest plugin to test Check_MK checks
Home-page: https://github.com/tom-mi/python-pytest-check_mk/
Author: Thomas Reifenberger
Author-email: tom-mi at rfnbrgr.de
License: GPLv2
Platform: any
Classifier: License :: OSI Approved :: GNU General Public License v2 (GPLv2)
Classifier: Programming Language :: Python
Classifier: Programming Language :: Python :: 2
Classifier: Programming Language :: Python :: 2.7
Classifier: Development Status :: 4 - Beta
Classifier: Intended Audience :: Developers
Classifier: Topic :: System :: Monitoring
Requires-Dist: pytest
